{"cameraMode":{"drawMode":0,"name":"Shaded","section":"Shading Mode"},"sceneLighting":true,"audioPlay":false,"sceneViewState":{"m_AlwaysRefresh":false,"showFog":true,"showSkybox":true,"showFlares":true,"showImageEffects":true,"showParticleSystems":true,"showVisualEffectGraphs":true,"m_FxEnabled":true},"in2DMode":false,"pivot":{"x":1.040900707244873,"y":0.8975958228111267,"z":7.070399761199951},"rotation":{"x":0.25139570236206057,"y":-0.6860878467559815,"z":0.27627018094062807,"w":0.6243147850036621},"size":3.897413969039917,"orthographic":false}